nvidia_riva_client-2.24.0.dist-info/licenses/LICENSE
riva/client/__init__.py
riva/client/argparse_utils.py
riva/client/asr.py
riva/client/audio_io.py
riva/client/auth.py
riva/client/health.py
riva/client/nlp.py
riva/client/nmt.py
riva/client/package_info.py
riva/client/realtime.py
riva/client/tts.py
riva/client/proto/__init__.py
riva/client/proto/health_pb2.py
riva/client/proto/health_pb2_grpc.py
riva/client/proto/riva_asr_pb2.py
riva/client/proto/riva_asr_pb2_grpc.py
riva/client/proto/riva_audio_pb2.py
riva/client/proto/riva_audio_pb2_grpc.py
riva/client/proto/riva_common_pb2.py
riva/client/proto/riva_common_pb2_grpc.py
riva/client/proto/riva_nlp_pb2.py
riva/client/proto/riva_nlp_pb2_grpc.py
riva/client/proto/riva_nmt_pb2.py
riva/client/proto/riva_nmt_pb2_grpc.py
riva/client/proto/riva_tts_pb2.py
riva/client/proto/riva_tts_pb2_grpc.py
nvidia_riva_client-2.24.0.dist-info/METADATA
nvidia_riva_client-2.24.0.dist-info/WHEEL
nvidia_riva_client-2.24.0.dist-info/top_level.txt
nvidia_riva_client-2.24.0.dist-info/RECORD
