Metadata-Version: 2.4
Name: nvidia-riva-client
Version: 2.24.0
Summary: Python implementation of the Riva Client API
Home-page: https://github.com/nvidia-riva/python-clients
Author: Anton Peganov
Author-email: apeganov@nvidia.com
Maintainer: Anton Peganov
Maintainer-email: apeganov@nvidia.com
License: MIT
Keywords: deep learning,machine learning,gpu,NLP,ASR,TTS,NMT,nvidia,speech,language,Riva,client
Classifier: Development Status :: 4 - Beta
Classifier: Intended Audience :: Developers
Classifier: Programming Language :: Python :: 3
Requires-Python: >=3.7
License-File: LICENSE
Requires-Dist: setuptools==78.1.1
Requires-Dist: grpcio==1.67.1
Requires-Dist: grpcio-tools==1.67.1
Requires-Dist: websockets==15.0.1
Dynamic: author
Dynamic: author-email
Dynamic: classifier
Dynamic: description
Dynamic: description-content-type
Dynamic: home-page
Dynamic: keywords
Dynamic: license
Dynamic: license-file
Dynamic: maintainer
Dynamic: maintainer-email
Dynamic: requires-dist
Dynamic: requires-python
Dynamic: summary
